{
    "name": "Laceration, Deflector of the East #3",
    "description": "Test Collection for Karambits",
    "image": "ipfs://NewUriToReplace",
    "dna": "something",
    "edition": "some edidition",
    "data": "2021-11-18",
    "attributes": {
        "environment_color_red": 0.69,
        "environment_color_green": 0.92,
        "environment_color_blue": 0.13,
        "blade_color_red": 0.77,
        "blade_color_green": 0.37,
        "blade_color_blue": 0.97,
        "handle_color_blue": 0.92
    }
}